mgz/__init__.py
mgz/cli.py
mgz/const.py
mgz/enums.py
mgz/reference.py
mgz/util.py
mgz/body/__init__.py
mgz/body/achievements.py
mgz/body/actions.py
mgz/body/embedded.py
mgz/common/__init__.py
mgz/common/chat.py
mgz/common/diplomacy.py
mgz/common/map.py
mgz/fast/__init__.py
mgz/fast/actions.py
mgz/fast/enums.py
mgz/fast/header.py
mgz/header/__init__.py
mgz/header/achievements.py
mgz/header/ai.py
mgz/header/de.py
mgz/header/hd.py
mgz/header/initial.py
mgz/header/lobby.py
mgz/header/map_info.py
mgz/header/objects.py
mgz/header/playerstats.py
mgz/header/replay.py
mgz/header/scenario.py
mgz/header/unit_type.py
mgz/model/__init__.py
mgz/model/compat.py
mgz/model/definitions.py
mgz/model/inputs.py
mgz/summary/__init__.py
mgz/summary/dataset.py
mgz/summary/full.py
mgz/summary/objects.py
mgz/summary/players.py
mgz/summary/settings.py
mgz/summary/teams.py
mgz-1.8.25.dist-info/LICENSE
mgz-1.8.25.dist-info/METADATA
mgz-1.8.25.dist-info/WHEEL
mgz-1.8.25.dist-info/entry_points.txt
mgz-1.8.25.dist-info/top_level.txt
mgz-1.8.25.dist-info/RECORD
