Metadata-Version: 2.1
Name: mgz
Version: 1.8.25
Summary: Parse Age of Empires 2 recorded games.
Home-page: https://github.com/happyleavesaoc/aoc-mgz/
Author: happyleaves
Author-email: happyleaves.tfr@gmail.com
License: MIT
Classifier: License :: OSI Approved :: MIT License
Classifier: Operating System :: OS Independent
Classifier: Programming Language :: Python :: 3
License-File: LICENSE
Requires-Dist: aocref >=2.0.17
Requires-Dist: construct ==2.8.16
Requires-Dist: tabulate >=0.9.0
Requires-Dist: dataclasses ==0.8 ; python_version < "3.7"
